edc_reportable/__init__.py
edc_reportable/admin_site.py
edc_reportable/adult_age_options.py
edc_reportable/age_evaluator.py
edc_reportable/apps.py
edc_reportable/auths.py
edc_reportable/choices.py
edc_reportable/constants.py
edc_reportable/evaluator.py
edc_reportable/exceptions.py
edc_reportable/formula.py
edc_reportable/post_migrate_signals.py
edc_reportable/reference_range_evaluator.py
edc_reportable/units.py
edc_reportable/urls.py
edc_reportable/admin/__init__.py
edc_reportable/admin/grading_data_admin.py
edc_reportable/admin/normal_data_admin.py
edc_reportable/data/__init__.py
edc_reportable/data/molecular_weights.py
edc_reportable/data/grading_data/__init__.py
edc_reportable/data/grading_data/ctcae_v5.py
edc_reportable/data/grading_data/daids_july_2017.py
edc_reportable/data/normal_data/__init__.py
edc_reportable/data/normal_data/africa.py
edc_reportable/forms/__init__.py
edc_reportable/forms/reportables_form_validator_mixin.py
edc_reportable/management/__init__.py
edc_reportable/management/commands/__init__.py
edc_reportable/management/commands/export_reportables.py
edc_reportable/migrations/0001_initial.py
edc_reportable/migrations/0002_alter_gradingdata_age_upper_and_more.py
edc_reportable/migrations/0003_referencerangecollection_grade1_and_more.py
edc_reportable/migrations/0004_alter_referencerangecollection_grade3_and_more.py
edc_reportable/migrations/0005_historicalnormaldata_auto_created_and_more.py
edc_reportable/migrations/__init__.py
edc_reportable/models/__init__.py
edc_reportable/models/grading_data.py
edc_reportable/models/grading_exception.py
edc_reportable/models/mw.py
edc_reportable/models/normal_data.py
edc_reportable/models/reference_model_mixins.py
edc_reportable/models/reference_range_collection.py
edc_reportable/tests/__init__.py
edc_reportable/tests/models.py
edc_reportable/tests/test_settings.py
edc_reportable/tests/urls.py
edc_reportable/tests/etc/user-aes-local.key
edc_reportable/tests/etc/user-aes-restricted.key
edc_reportable-2.0.2.dist-info/licenses/AUTHORS.rst
edc_reportable-2.0.2.dist-info/licenses/LICENSE
edc_reportable-2.0.2.dist-info/METADATA
edc_reportable-2.0.2.dist-info/WHEEL
edc_reportable-2.0.2.dist-info/top_level.txt
edc_reportable-2.0.2.dist-info/RECORD
