Metadata-Version: 2.4
Name: edc-reportable
Version: 2.0.2
Summary: Reportable clinic events, reference ranges, grading for clinicedc/edc projects
Home-page: https://github.com/clinicedc/edc-reportable
Author: Erik van Widenfelt
Author-email: ew2789@gmail.com
License: GPL license, see LICENSE
Keywords: django,edc,DAIDS,reference ranges,normal ranges,clinicedc,clinical trials
Classifier: Environment :: Web Environment
Classifier: Framework :: Django
Classifier: Framework :: Django :: 5.1
Classifier: Intended Audience :: Developers
Classifier: Intended Audience :: Science/Research
Classifier: Operating System :: OS Independent
Classifier: Programming Language :: Python :: 3.12
Classifier: License :: OSI Approved :: GNU General Public License v3 (GPLv3)
Requires-Python: >=3.12
License-File: LICENSE
License-File: AUTHORS.rst
Dynamic: license-file
